<?xml version="1.0" encoding="UTF-8" ?>
<!DOCTYPE mapper PUBLIC "-//mybatis.org//DTD Mapper 3.0//EN" "http://mybatis.org/dtd/mybatis-3-mapper.dtd" >
<mapper namespace="com.mark.test.framework.core.dao.OpenAgreementDetermineMapper" >
  <resultMap id="BaseResultMap" type="com.mark.test.framework.core.dto.OpenAgreementDetermine" >
    <!--
      WARNING - @mbggenerated
      This element is automatically generated by MyBatis Generator, do not modify.
    -->
    <constructor >
      <idArg column="orderNo" jdbcType="VARCHAR" javaType="java.lang.String" />
      <arg column="reqNo" jdbcType="VARCHAR" javaType="java.lang.String" />
      <arg column="customerId" jdbcType="VARCHAR" javaType="java.lang.String" />
      <arg column="smsSeq" jdbcType="VARCHAR" javaType="java.lang.String" />
      <arg column="authCode" jdbcType="VARCHAR" javaType="java.lang.String" />
      <arg column="custAccountId" jdbcType="VARCHAR" javaType="java.lang.String" />
      <arg column="holderName" jdbcType="VARCHAR" javaType="java.lang.String" />
      <arg column="bankCardNo" jdbcType="VARCHAR" javaType="java.lang.String" />
      <arg column="status" jdbcType="VARCHAR" javaType="java.lang.String" />
      <arg column="treatyNo" jdbcType="VARCHAR" javaType="java.lang.String" />
      <arg column="failureDetails" jdbcType="VARCHAR" javaType="java.lang.String" />
      <arg column="errorCode" jdbcType="VARCHAR" javaType="java.lang.String" />
      <arg column="sendDate" jdbcType="TIMESTAMP" javaType="java.util.Date" />
      <arg column="returnDate" jdbcType="TIMESTAMP" javaType="java.util.Date" />
      <arg column="updateDate" jdbcType="TIMESTAMP" javaType="java.util.Date" />
      <arg column="source" jdbcType="VARCHAR" javaType="java.lang.String" />
    </constructor>
  </resultMap>


  <sql id="Base_Column_List" >
    <!--
      WARNING - @mbggenerated
      This element is automatically generated by MyBatis Generator, do not modify.
    -->
    orderNo, reqNo, customerId, smsSeq, authCode, custAccountId, holderName, bankCardNo, 
    status, treatyNo, failureDetails, errorCode, sendDate, returnDate, updateDate, source
  </sql>


  <insert id="insertSelective" parameterType="com.mark.test.framework.core.dto.OpenAgreementDetermine" >
    <!--
      WARNING - @mbggenerated
      This element is automatically generated by MyBatis Generator, do not modify.
    -->
    insert into open_agreement_determine
    <trim prefix="(" suffix=")" suffixOverrides="," >
      <if test="orderno != null" >
        orderNo,
      </if>
      <if test="reqno != null" >
        reqNo,
      </if>
      <if test="customerid != null" >
        customerId,
      </if>
      <if test="smsseq != null" >
        smsSeq,
      </if>
      <if test="authcode != null" >
        authCode,
      </if>
      <if test="custaccountid != null" >
        custAccountId,
      </if>
      <if test="holdername != null" >
        holderName,
      </if>
      <if test="bankcardno != null" >
        bankCardNo,
      </if>
      <if test="status != null" >
        status,
      </if>
      <if test="treatyno != null" >
        treatyNo,
      </if>
      <if test="failuredetails != null" >
        failureDetails,
      </if>
      <if test="errorcode != null" >
        errorCode,
      </if>
      <if test="senddate != null" >
        sendDate,
      </if>
      <if test="returndate != null" >
        returnDate,
      </if>
      <if test="updatedate != null" >
        updateDate,
      </if>
      <if test="source != null" >
        source,
      </if>
    </trim>
    <trim prefix="values (" suffix=")" suffixOverrides="," >
      <if test="orderno != null" >
        #{orderno,jdbcType=VARCHAR},
      </if>
      <if test="reqno != null" >
        #{reqno,jdbcType=VARCHAR},
      </if>
      <if test="customerid != null" >
        #{customerid,jdbcType=VARCHAR},
      </if>
      <if test="smsseq != null" >
        #{smsseq,jdbcType=VARCHAR},
      </if>
      <if test="authcode != null" >
        #{authcode,jdbcType=VARCHAR},
      </if>
      <if test="custaccountid != null" >
        #{custaccountid,jdbcType=VARCHAR},
      </if>
      <if test="holdername != null" >
        #{holdername,jdbcType=VARCHAR},
      </if>
      <if test="bankcardno != null" >
        #{bankcardno,jdbcType=VARCHAR},
      </if>
      <if test="status != null" >
        #{status,jdbcType=VARCHAR},
      </if>
      <if test="treatyno != null" >
        #{treatyno,jdbcType=VARCHAR},
      </if>
      <if test="failuredetails != null" >
        #{failuredetails,jdbcType=VARCHAR},
      </if>
      <if test="errorcode != null" >
        #{errorcode,jdbcType=VARCHAR},
      </if>
      <if test="senddate != null" >
        #{senddate,jdbcType=TIMESTAMP},
      </if>
      <if test="returndate != null" >
        #{returndate,jdbcType=TIMESTAMP},
      </if>
      <if test="updatedate != null" >
        #{updatedate,jdbcType=TIMESTAMP},
      </if>
      <if test="source != null" >
        #{source,jdbcType=VARCHAR},
      </if>
    </trim>
  </insert>


  <update id="updateByPrimaryKeySelective" parameterType="com.mark.test.framework.core.dto.OpenAgreementDetermine" >
    <!--
      WARNING - @mbggenerated
      This element is automatically generated by MyBatis Generator, do not modify.
    -->
    update open_agreement_determine
    <set >
      <if test="reqno != null" >
        reqNo = #{reqno,jdbcType=VARCHAR},
      </if>
      <if test="customerid != null" >
        customerId = #{customerid,jdbcType=VARCHAR},
      </if>
      <if test="smsseq != null" >
        smsSeq = #{smsseq,jdbcType=VARCHAR},
      </if>
      <if test="authcode != null" >
        authCode = #{authcode,jdbcType=VARCHAR},
      </if>
      <if test="custaccountid != null" >
        custAccountId = #{custaccountid,jdbcType=VARCHAR},
      </if>
      <if test="holdername != null" >
        holderName = #{holdername,jdbcType=VARCHAR},
      </if>
      <if test="bankcardno != null" >
        bankCardNo = #{bankcardno,jdbcType=VARCHAR},
      </if>
      <if test="status != null" >
        status = #{status,jdbcType=VARCHAR},
      </if>
      <if test="treatyno != null" >
        treatyNo = #{treatyno,jdbcType=VARCHAR},
      </if>
      <if test="failuredetails != null" >
        failureDetails = #{failuredetails,jdbcType=VARCHAR},
      </if>
      <if test="errorcode != null" >
        errorCode = #{errorcode,jdbcType=VARCHAR},
      </if>
      <if test="senddate != null" >
        sendDate = #{senddate,jdbcType=TIMESTAMP},
      </if>
      <if test="returndate != null" >
        returnDate = #{returndate,jdbcType=TIMESTAMP},
      </if>
      <if test="updatedate != null" >
        updateDate = #{updatedate,jdbcType=TIMESTAMP},
      </if>
      <if test="source != null" >
        source = #{source,jdbcType=VARCHAR},
      </if>
    </set>
    where orderNo = #{orderno,jdbcType=VARCHAR}
  </update>
</mapper>